emojis/__init__.py
emojis/emojis.py
emojis/utils.py
emojis/database/data.json
emojis/database/messages.json
emojis/database/metadata.json
emojis/database/shortcodes.json
emojis_py-1.3.0.dist-info/licenses/LICENSE
emojis_py-1.3.0.dist-info/METADATA
emojis_py-1.3.0.dist-info/WHEEL
emojis_py-1.3.0.dist-info/top_level.txt
emojis_py-1.3.0.dist-info/RECORD
