Metadata-Version: 2.4
Name: emojis.py
Version: 1.3.0
Summary: A basic emoji manipulator for Python.
Home-page: https://github.com/Ombucha/emojis.py
Author: Omkaar
Author-email: omkaar.nerurkar@gmail.com
License: MIT
Classifier: License :: OSI Approved :: MIT License
Classifier: Natural Language :: English
Classifier: Programming Language :: Python
Classifier: Programming Language :: Python :: 3
Requires-Python: >= 3.8.0
License-File: LICENSE
Dynamic: author
Dynamic: author-email
Dynamic: classifier
Dynamic: description
Dynamic: description-content-type
Dynamic: home-page
Dynamic: license
Dynamic: license-file
Dynamic: requires-python
Dynamic: summary
